ps2ff/__init__.py
ps2ff/cmd.py
ps2ff/config.py
ps2ff/constants.py
ps2ff/integration_loops.py
ps2ff/interpolate.py
ps2ff/magnitude_scaling.py
ps2ff/run.py
ps2ff/bin/Cy14HwMeanVar.py
ps2ff/bin/__init__.py
ps2ff/bin/run_ps2ff.py
ps2ff/bin/run_ps2ff_single_event.py
ps2ff/config/acr_n.ini
ps2ff/config/acr_r.ini
ps2ff/config/acr_ss.ini
ps2ff/config/default.ini
ps2ff/config/scr_a.ini
ps2ff/config/scr_n.ini
ps2ff/config/scr_r.ini
ps2ff/config/scr_ss.ini
ps2ff/data/configspec.conf
ps2ff/tables/Rjb_HB08_mechN_ar1p7_seis0_20_Ratios.csv
ps2ff/tables/Rjb_HB08_mechN_ar1p7_seis0_20_Var.csv
ps2ff/tables/Rjb_HB08_mechR_ar1p7_seis0_20_Ratios.csv
ps2ff/tables/Rjb_HB08_mechR_ar1p7_seis0_20_Var.csv
ps2ff/tables/Rjb_HB08_mechSS_ar1p7_seis0_20_Ratios.csv
ps2ff/tables/Rjb_HB08_mechSS_ar1p7_seis0_20_Var.csv
ps2ff/tables/Rjb_S14_mechA_ar1p0_seis0_15_Ratios.csv
ps2ff/tables/Rjb_S14_mechA_ar1p0_seis0_15_Var.csv
ps2ff/tables/Rjb_S14_mechN_ar1p0_seis0_15_Ratios.csv
ps2ff/tables/Rjb_S14_mechN_ar1p0_seis0_15_Var.csv
ps2ff/tables/Rjb_S14_mechR_ar1p0_seis0_15_Ratios.csv
ps2ff/tables/Rjb_S14_mechR_ar1p0_seis0_15_Var.csv
ps2ff/tables/Rjb_S14_mechSS_ar1p0_seis0_15_Ratios.csv
ps2ff/tables/Rjb_S14_mechSS_ar1p0_seis0_15_Var.csv
ps2ff/tables/Rjb_WC94_mechA_ar1p7_seis0_20_Ratios.csv
ps2ff/tables/Rjb_WC94_mechA_ar1p7_seis0_20_Var.csv
ps2ff/tables/Rrup_HB08_mechN_ar1p7_seis0_20_Ratios.csv
ps2ff/tables/Rrup_HB08_mechN_ar1p7_seis0_20_Var.csv
ps2ff/tables/Rrup_HB08_mechR_ar1p7_seis0_20_Ratios.csv
ps2ff/tables/Rrup_HB08_mechR_ar1p7_seis0_20_Var.csv
ps2ff/tables/Rrup_HB08_mechSS_ar1p7_seis0_20_Ratios.csv
ps2ff/tables/Rrup_HB08_mechSS_ar1p7_seis0_20_Var.csv
ps2ff/tables/Rrup_S14_mechA_ar1p0_seis0_15_Ratios.csv
ps2ff/tables/Rrup_S14_mechA_ar1p0_seis0_15_Var.csv
ps2ff/tables/Rrup_S14_mechN_ar1p0_seis0_15_Ratios.csv
ps2ff/tables/Rrup_S14_mechN_ar1p0_seis0_15_Var.csv
ps2ff/tables/Rrup_S14_mechR_ar1p0_seis0_15_Ratios.csv
ps2ff/tables/Rrup_S14_mechR_ar1p0_seis0_15_Var.csv
ps2ff-1.5.8.dist-info/LICENSE.md
ps2ff-1.5.8.dist-info/METADATA
ps2ff-1.5.8.dist-info/WHEEL
ps2ff-1.5.8.dist-info/entry_points.txt
ps2ff-1.5.8.dist-info/top_level.txt
ps2ff-1.5.8.dist-info/RECORD
