Metadata-Version: 2.1
Name: ps2ff
Version: 1.5.8
Summary: Approximated rupture distances from point source
Author-email: Eric Thompson <emthompsone@usgs.gov>, Bruce Worden <cbworden@contractor.usgs.gov>
License: License
Requires-Python: >=3.9
License-File: LICENSE.md
Requires-Dist: configobj>=5.0.6
Requires-Dist: numpy<2.0,>=1.21
Requires-Dist: pandas>=1.0
Requires-Dist: scipy>=1.7
Provides-Extra: build
Requires-Dist: build; extra == "build"
Requires-Dist: twine; extra == "build"
Provides-Extra: dev
Requires-Dist: build>=0.7.0; extra == "dev"
Requires-Dist: black>=21; extra == "dev"
Requires-Dist: esi-releases>=0.1; extra == "dev"
Requires-Dist: flake8>=3.9; extra == "dev"
Requires-Dist: ipython>=7.26; extra == "dev"
Requires-Dist: pylint>=2.17; extra == "dev"
Provides-Extra: doc
Requires-Dist: altair>=4.2.2; extra == "doc"
Requires-Dist: furo>=2023.3.27; extra == "doc"
Requires-Dist: myst-nb>=0.17.2; extra == "doc"
Requires-Dist: myst-parser>=0.18.1; extra == "doc"
Requires-Dist: nbsphinx>=0.9.1; extra == "doc"
Requires-Dist: recommonmark>=0.7.1; extra == "doc"
Requires-Dist: sphinx>5.0.0; extra == "doc"
Requires-Dist: sphinx-autoapi<3.0.0; extra == "doc"
Requires-Dist: sphinx-copybutton>=0.5.2; extra == "doc"
Requires-Dist: sphinx-inline-tabs>=2023.4.21; extra == "doc"
Requires-Dist: sphinxcontrib-programoutput>=0.17; extra == "doc"
Provides-Extra: test
Requires-Dist: pytest>=6.2; extra == "test"
Requires-Dist: pytest-cov>=2.12; extra == "test"
Requires-Dist: pytest-console-scripts>=1.4; extra == "test"
Requires-Dist: vcrpy>=4.1; extra == "test"
